pymacnet/__init__.py
pymacnet/channel_interface.py
pymacnet/cycler_interface.py
pymacnet/maccorspoofer/MaccorSpoofer.py
pymacnet/maccorspoofer/__init__.py
pymacnet/messages/__init__.py
pymacnet/messages/messages.py
pymacnet/messages/status_dictionary.py
pymacnet-1.1.3.dist-info/LICENSE
pymacnet-1.1.3.dist-info/METADATA
pymacnet-1.1.3.dist-info/WHEEL
pymacnet-1.1.3.dist-info/top_level.txt
pymacnet-1.1.3.dist-info/RECORD
