Metadata-Version: 2.1
Name: pymacnet
Version: 1.1.3
Summary: A class based python interface for communication and control of Maccor cyclers over Macnet.
Home-page: https://github.com/BattGenie/pymacnet.git
Author: Bing Syuan Wang, Chintan Pathak and Zander Nevitt
Author-email: info@battgenie.life
License: MIT
Classifier: Programming Language :: Python :: 3
Classifier: License :: OSI Approved :: MIT License
Classifier: Operating System :: OS Independent
Requires-Python: >=3.6
License-File: LICENSE
